{
	"categories": [
		{
			"value": 72,
			"item": "laptop"
		},
		{
			"value": 94,
			"item": "shoes"
		},
		{
			"value": 15,
			"item": "camera"
		},
		{
			"value": 65,
			"item": "jeans"
		},
		{
			"value": 78,
			"item": "mobile"
		},
		{
			"value": 47,
			"item": "keyboard"
		},
		{
			"value": 54,
			"item": "mouse"
		}
	],

	"transaction": [
		{
			"id": 1,
			"amount": 5902,
			"quantity": 5,
			"discount": 900,
			"status": "processing"
		},
		{
			"id": 1,
			"amount": 5902,
			"quantity": 5,
			"discount": 900,
			"status": "shipped"
		},
		{
			"id": 1,
			"amount": 5902,
			"quantity": 5,
			"discount": 900,
			"status": "delivered"
		},
		{
			"id": 1,
			"amount": 5902,
			"quantity": 5,
			"discount": 900,
			"status": "processing"
		},
		{
			"id": 1,
			"amount": 5902,
			"quantity": 5,
			"discount": 900,
			"status": "shipped"
		},
		{
			"id": 1,
			"amount": 5902,
			"quantity": 5,
			"discount": 900,
			"status": "delivered"
		},
		{
			"id": 1,
			"amount": 5902,
			"quantity": 5,
			"discount": 900,
			"status": "processing"
		},
		{
			"id": 1,
			"amount": 5902,
			"quantity": 5,
			"discount": 900,
			"status": "processing"
		},
		{
			"id": 1,
			"amount": 5902,
			"quantity": 5,
			"discount": 900,
			"status": "shipped"
		},
		{
			"id": 1,
			"amount": 5902,
			"quantity": 5,
			"discount": 900,
			"status": "delivered"
		}
	]
}
